eventity/__init__.py
eventity/component.py
eventity/entity.py
eventity/entityfileparser.py
eventity/eventity_core.py
eventity/eventmanager.py
eventity/system.py
eventity-0.3.1.dist-info/DESCRIPTION.rst
eventity-0.3.1.dist-info/METADATA
eventity-0.3.1.dist-info/RECORD
eventity-0.3.1.dist-info/WHEEL
eventity-0.3.1.dist-info/metadata.json
eventity-0.3.1.dist-info/top_level.txt
