Metadata-Version: 2.0
Name: eventity
Version: 0.3.1
Summary: Easy event based ECS system
Home-page: https://github.com/JonSnowbd/Eventity
Author: Josiah P.
Author-email: vasti009@gmail.com
License: MIT
Keywords: event entity component system ecs
Platform: UNKNOWN
